MANIFEST.in
README.md
build.py
requirements-dev.txt
requirements.txt
setup.py
pyvideo/__init__.py
pyvideo/audio.py
pyvideo/video.py
pyvideoio.egg-info/PKG-INFO
pyvideoio.egg-info/SOURCES.txt
pyvideoio.egg-info/dependency_links.txt
pyvideoio.egg-info/requires.txt
pyvideoio.egg-info/top_level.txt